openerp_proxy/__init__.py
openerp_proxy/core.py
openerp_proxy/exceptions.py
openerp_proxy/main.py
openerp_proxy/plugin.py
openerp_proxy/session.py
openerp_proxy/utils.py
openerp_proxy/version.py
openerp_proxy/connection/__init__.py
openerp_proxy/experimental/__init__.py
openerp_proxy/experimental/ipy_utils.py
openerp_proxy/experimental/onchange.py
openerp_proxy/experimental/relations.py
openerp_proxy/experimental/utils.py
openerp_proxy/ext/__init__.py
openerp_proxy/ext/all.py
openerp_proxy/ext/field_datetime.py
openerp_proxy/ext/log_execute_console.py
openerp_proxy/ext/sugar.py
openerp_proxy/ext/workflow.py
openerp_proxy/ext/repr/__init__.py
openerp_proxy/ext/repr/generic.py
openerp_proxy/ext/repr/orm.py
openerp_proxy/ext/repr/reports.py
openerp_proxy/ext/repr/utils.py
openerp_proxy/orm/__init__.py
openerp_proxy/orm/cache.py
openerp_proxy/orm/object.py
openerp_proxy/orm/record.py
openerp_proxy/orm/service.py
openerp_proxy/plugins/__init__.py
openerp_proxy/plugins/external_ids.py
openerp_proxy/plugins/module_utils.py
openerp_proxy/plugins/diagraming/__init__.py
openerp_proxy/plugins/diagraming/graph.py
openerp_proxy/plugins/diagraming/graphml_yed.py
openerp_proxy/service/__init__.py
openerp_proxy/service/db.py
openerp_proxy/service/object.py
openerp_proxy/service/report.py
openerp_proxy/service/service.py
openerp_proxy/tests/__init__.py
openerp_proxy/tests/all.py
openerp_proxy/tests/test_client.py
openerp_proxy/tests/test_connection.py
openerp_proxy/tests/test_db.py
openerp_proxy/tests/test_ipynb.py
openerp_proxy/tests/test_main.py
openerp_proxy/tests/test_orm.py
openerp_proxy/tests/test_plugins.py
openerp_proxy/tests/test_session.py
openerp_proxy/tests/test_utils.py
openerp_proxy-1.0.0.data/scripts/openerp_proxy
openerp_proxy-1.0.0.dist-info/METADATA
openerp_proxy-1.0.0.dist-info/RECORD
openerp_proxy-1.0.0.dist-info/WHEEL
openerp_proxy-1.0.0.dist-info/top_level.txt
