Metadata-Version: 2.1
Name: openerp-proxy
Version: 1.0.0
Summary: Odoo/OpenERP CLI interface and library for RPC
Home-page: https://github.com/katyukha/openerp-proxy
Author: Dmytro Katyukha
Author-email: firemage.dima@gmail.com
License: GPL
Keywords: openerp,odoo,odoo-rpc,rpc,xmlrpc,xml-rpc,json-rpc,jsonrpc,odoo-client,ipython
Platform: UNKNOWN
Classifier: Development Status :: 4 - Beta
Classifier: Environment :: Console
Classifier: Intended Audience :: Developers
Classifier: License :: OSI Approved :: GNU General Public License (GPL)
Classifier: Programming Language :: Python
Classifier: Programming Language :: Python :: 2
Classifier: Programming Language :: Python :: 2.7
Classifier: Programming Language :: Python :: 3
Classifier: Programming Language :: Python :: 3.3
Classifier: Programming Language :: Python :: 3.4
Classifier: Programming Language :: Python :: 3.5
Classifier: Programming Language :: Python :: Implementation :: CPython
Classifier: Topic :: Utilities
Classifier: Topic :: Software Development :: Libraries
Classifier: Topic :: Software Development :: Libraries :: Python Modules
Provides-Extra: all
Requires-Dist: tabulate (>=0.7.5)
Requires-Dist: six (>=1.10)
Requires-Dist: extend-me (>=1.1.3)
Requires-Dist: setuptools (>=18)
Requires-Dist: requests (>=2.7)
Requires-Dist: ipython (>=4)
Requires-Dist: Jinja2
Requires-Dist: odoo-rpc-client (>=0.9.0)
Provides-Extra: all
Requires-Dist: ipython[all]; extra == 'all'
Requires-Dist: anyfield; extra == 'all'
